open_image_models/__init__.py
open_image_models/detection/__init__.py
open_image_models/detection/core/__init__.py
open_image_models/detection/core/base.py
open_image_models/detection/core/hub.py
open_image_models/detection/core/yolo_v9/__init__.py
open_image_models/detection/core/yolo_v9/inference.py
open_image_models/detection/core/yolo_v9/postprocess.py
open_image_models/detection/core/yolo_v9/preprocess.py
open_image_models/detection/pipeline/__init__.py
open_image_models/detection/pipeline/license_plate.py
open_image_models/py.typed
open_image_models/utils.py
open_image_models-0.4.0.dist-info/LICENSE
open_image_models-0.4.0.dist-info/METADATA
open_image_models-0.4.0.dist-info/WHEEL
open_image_models-0.4.0.dist-info/RECORD
