Metadata-Version: 2.3
Name: open-image-models
Version: 0.4.0
Summary: Pre-trained image models using ONNX for fast, out-of-the-box inference.
License: MIT
Keywords: image-processing,computer-vision,deep-learning,image-classification,object-detection,open-source-models,onnx
Author: ankandrew
Author-email: 61120139+ankandrew@users.noreply.github.com
Requires-Python: >=3.10,<4.0
Classifier: Intended Audience :: Developers
Classifier: Intended Audience :: Education
Classifier: Intended Audience :: Science/Research
Classifier: License :: OSI Approved :: MIT License
Classifier: Operating System :: OS Independent
Classifier: Programming Language :: Python :: 3
Classifier: Programming Language :: Python :: 3.10
Classifier: Programming Language :: Python :: 3.11
Classifier: Programming Language :: Python :: 3.12
Classifier: Programming Language :: Python :: 3.13
Classifier: Topic :: Scientific/Engineering
Classifier: Topic :: Scientific/Engineering :: Artificial Intelligence
Classifier: Topic :: Software Development
Classifier: Topic :: Software Development :: Build Tools
Classifier: Topic :: Software Development :: Libraries
Classifier: Topic :: Software Development :: Libraries :: Python Modules
Classifier: Typing :: Typed
Provides-Extra: onnx
Provides-Extra: onnx-directml
Provides-Extra: onnx-gpu
Provides-Extra: onnx-openvino
Provides-Extra: onnx-qnn
Requires-Dist: numpy
Requires-Dist: onnxruntime (>=1.19.2) ; extra == "onnx"
Requires-Dist: onnxruntime-directml (>=1.19.2) ; extra == "onnx-directml"
Requires-Dist: onnxruntime-gpu (>=1.19.2) ; extra == "onnx-gpu"
Requires-Dist: onnxruntime-openvino (>=1.19.2) ; extra == "onnx-openvino"
Requires-Dist: onnxruntime-qnn (>=1.19.2) ; extra == "onnx-qnn"
Requires-Dist: opencv-python
Requires-Dist: rich
Requires-Dist: tqdm
Project-URL: Repository, https://github.com/ankandrew/open-image-models
